themecor/__init__.py
themecor/cli.py
themecor/theme_manager.py
themecor-0.1.0.dist-info/LICENSE
themecor-0.1.0.dist-info/METADATA
themecor-0.1.0.dist-info/WHEEL
themecor-0.1.0.dist-info/entry_points.txt
themecor-0.1.0.dist-info/RECORD
