Metadata-Version: 2.1
Name: themecor
Version: 0.1.0
Summary: `themecor` is a Python package that provides a centralized theme manager to ensure visual consistency across different packages within an application. It offers styles and methods to display messages, prompts, and progress bars in a uniform manner.
License: MIT
Author: infocornouaille
Author-email: 90894019+infocornouaille@users.noreply.github.com
Requires-Python: >=3.12,<4.0
Classifier: Development Status :: 3 - Alpha
Classifier: License :: OSI Approved :: MIT License
Classifier: Operating System :: OS Independent
Classifier: Programming Language :: Python :: 3
Classifier: Programming Language :: Python :: 3.12
Classifier: Topic :: Software Development :: Libraries :: Python Modules
Requires-Dist: rich (>=13.9.4,<14.0.0)
Requires-Dist: typer (>=0.15.1,<0.16.0)
